Biryani-0.10.8.dist-info/METADATA
Biryani-0.10.8.dist-info/RECORD
Biryani-0.10.8.dist-info/WHEEL
Biryani-0.10.8.dist-info/top_level.txt
biryani/__init__.py
biryani/babelconv.py
biryani/base64conv.py
biryani/baseconv.py
biryani/bsonconv.py
biryani/creditcardconv.py
biryani/datetimeconv.py
biryani/frconv.py
biryani/gcm.py
biryani/jsonconv.py
biryani/jwkconv.py
biryani/jwtconv.py
biryani/netconv.py
biryani/objectconv.py
biryani/states.py
biryani/strings.py
biryani/uuidconv.py
biryani/webobconv.py
biryani/i18n/biryani.pot
biryani/i18n/fr/LC_MESSAGES/biryani.po
biryani/nonstandard/__init__.py
biryani/nonstandard/deprecatedbaseconv.py
biryani/nonstandard/experimentalbaseconv.py
